tfcoreml/__init__.py
tfcoreml/_interpret_shapes.py
tfcoreml/_layers.py
tfcoreml/_layers_common.py
tfcoreml/_ops_to_layers.py
tfcoreml/_shape_sensitive_layers.py
tfcoreml/_tf_coreml_converter.py
tfcoreml/_tf_graph_transform.py
tfcoreml/optimizations/__init__.py
tfcoreml/optimizations/_optimize.py
tfcoreml/optimizations/_optimize_nn_spec.py
tfcoreml-2.0.dist-info/AUTHORS
tfcoreml-2.0.dist-info/LICENSE
tfcoreml-2.0.dist-info/METADATA
tfcoreml-2.0.dist-info/WHEEL
tfcoreml-2.0.dist-info/top_level.txt
tfcoreml-2.0.dist-info/RECORD
