Metadata-Version: 2.1
Name: tfcoreml
Version: 2.0
Summary: TensorFlow to Core ML converter
Home-page: https://github.com/tf-coreml/tf-coreml
Author: tfcoreml
Author-email: tf-coreml@apple.com
License: Apache 2.0
Keywords: Converter TensorFlow Core ML
Platform: UNKNOWN
Classifier: Development Status :: 5 - Production/Stable
Classifier: Intended Audience :: End Users/Desktop
Classifier: Intended Audience :: Developers
Classifier: Operating System :: MacOS :: MacOS X
Classifier: Topic :: Scientific/Engineering
Classifier: Topic :: Software Development
Classifier: Programming Language :: Python :: 2.7
Classifier: Programming Language :: Python :: 3.5
Classifier: Programming Language :: Python :: 3.6
Classifier: Programming Language :: Python :: 3.7
Requires-Dist: numpy (>=1.6.2)
Requires-Dist: protobuf (>=3.1.0)
Requires-Dist: six (>=1.10.0)
Requires-Dist: tensorflow (<=1.14,>=1.5.0)
Requires-Dist: coremltools (>=0.8)
